plum/__init__.py
plum/_version.py
plum/alias.py
plum/autoreload.py
plum/dispatcher.py
plum/function.py
plum/overload.py
plum/parametric.py
plum/promotion.py
plum/py.typed
plum/resolver.py
plum/signature.py
plum/type.py
plum/util.py
cola_plum_dispatch-0.1.4.dist-info/METADATA
cola_plum_dispatch-0.1.4.dist-info/WHEEL
cola_plum_dispatch-0.1.4.dist-info/licenses/LICENCE.txt
cola_plum_dispatch-0.1.4.dist-info/RECORD
